{
  "groups": [
    {
      "name": "Group 1",
      "players": [
        {
          "name": "Tayla Bailey",
          "club": "Boundary"
        },
        {
          "name": "Shiloh Smith",
          "club": "Top"
        },
        {
          "name": "Skylyn Joseph",
          "club": "Top"
        }
      ]
    },
    {
      "name": "Group 2",
      "players": [
        {
          "name": "Jade Sasman",
          "club": "Boundary"
        },
        {
          "name": "Jody Theunissen",
          "club": "Top"
        },
        {
          "name": "Xoey Williams",
          "club": "Top"
        }
      ]
    },
    {
      "name": "Group 3",
      "players": [
        {
          "name": "Ashley Tsai",
          "club": "Community House"
        },
        {
          "name": "Logan Willemse",
          "club": "Top"
        },
        {
          "name": "Christina Malan",
          "club": "Maties"
        }
      ]
    }
  ]
}